joshsqlite/__init__.py
joshsqlite/query.py
joshsqlite/result.py
joshsqlite/schema.py
joshsqlite/sqlite3worker.py
joshsqlite/store.py
joshsqlite-0.0.3.dist-info/LICENSE.txt
joshsqlite-0.0.3.dist-info/METADATA
joshsqlite-0.0.3.dist-info/WHEEL
joshsqlite-0.0.3.dist-info/top_level.txt
joshsqlite-0.0.3.dist-info/RECORD
